{"cameraMode":{"drawMode":0,"name":"Shaded","section":"Shading Mode"},"sceneLighting":true,"audioPlay":false,"sceneViewState":{"showFog":true,"showMaterialUpdate":false,"showSkybox":true,"showFlares":true,"showImageEffects":true,"showParticleSystems":true,"showVisualEffectGraphs":true,"m_FxEnabled":true},"in2DMode":false,"pivot":{"x":6.135969638824463,"y":0.8711738586425781,"z":5.563317775726318},"rotation":{"x":-0.5676842927932739,"y":0.020498821511864663,"z":-0.014148436486721039,"w":-0.8228780627250671},"size":21.14947509765625,"orthographic":false}